dominion/__init__.py
dominion/cards/__init__.py
dominion/cards/action.py
dominion/cards/card.py
dominion/cards/curse.py
dominion/cards/expansions/__init__.py
dominion/cards/expansions/first_edition.py
dominion/cards/expansions/intrigue_first_edition.py
dominion/cards/expansions/intrigue_second_edition.py
dominion/cards/expansions/second_edition.py
dominion/cards/treasure.py
dominion/cards/victory.py
dominion/deck.py
dominion/errors.py
dominion/event.py
dominion/game.py
dominion/player.py
dominion/py.typed
dominion/report.py
pydominion-0.1.0.dist-info/LICENSE
pydominion-0.1.0.dist-info/WHEEL
pydominion-0.1.0.dist-info/METADATA
pydominion-0.1.0.dist-info/RECORD
