Metadata-Version: 2.1
Name: pydominion
Version: 0.1.0
Summary: Play the infamous medieval deck-building strategy game in Python!
Home-page: https://github.com/GrandMoff100/PyDominion
License: GPL-3.0-or-later
Author: Nate
Author-email: minecraftcrusher100@gmail.com
Requires-Python: >=3.8,<4.0
Classifier: License :: OSI Approved :: GNU General Public License v3 or later (GPLv3+)
Classifier: Programming Language :: Python :: 3
Classifier: Programming Language :: Python :: 3.10
Classifier: Programming Language :: Python :: 3.8
Classifier: Programming Language :: Python :: 3.9
Project-URL: Repository, https://github.com/GrandMoff100/PyDominion
